equator/__init__.py
equator/__main__.py
equator/equator.py
equator/eq_curses/__init__.py
equator/eq_curses/colours.py
equator/eq_curses/curses_main.py
equator/eq_curses/display_exp.py
equator/eq_curses/input_container.py
equator/eq_curses/output_container.py
equator/eq_json/__init__.py
equator/eq_json/json_main.py
equator/lib/__init__.py
equator/lib/consts.py
equator/lib/eq_except.py
equator/lib/eq_object.py
equator/lib/expression.py
equator/lib/main.py
equator/lib/operation.py
equator/lib/output_formatter.py
equator/lib/parsedinput.py
equator/lib/segment.py
equator/lib/subexpression.py
equator/lib/tokens.py
equatorpy-1.2.1.dist-info/LICENSE.txt
equatorpy-1.2.1.dist-info/METADATA
equatorpy-1.2.1.dist-info/WHEEL
equatorpy-1.2.1.dist-info/entry_points.txt
equatorpy-1.2.1.dist-info/top_level.txt
equatorpy-1.2.1.dist-info/RECORD
