Metadata-Version: 2.1
Name: equatorpy
Version: 1.2.1
Summary: An advanced symbolic calculator and maths interpreter
Home-page: https://github.com/MiguelGuthridge/Equator
Author: Miguel Guthridge
Author-email: hdsq@outlook.com.au
License: UNKNOWN
Project-URL: Bug Tracker, https://github.com/MiguelGuthridge/Equator/issues
Keywords: equator,calculator,symbolic,math,equation,sympy,json,cli
Platform: UNKNOWN
Classifier: Programming Language :: Python :: 3
Classifier: Intended Audience :: Education
Classifier: License :: OSI Approved :: GNU General Public License v3 (GPLv3)
Classifier: Operating System :: OS Independent
Classifier: Development Status :: 5 - Production/Stable
Classifier: Environment :: Console
Classifier: Environment :: Console :: Curses
Requires-Python: >=3.6
License-File: LICENSE.txt
Requires-Dist: sympy
Requires-Dist: colorama
Requires-Dist: windows-curses (>=2.2.0) ; platform_system == "Windows"
